pymt_topography-0.1.3.dist-info/METADATA
pymt_topography-0.1.3.dist-info/WHEEL
pymt_topography-0.1.3.dist-info/entry_points.txt
pymt_topography-0.1.3.dist-info/LICENSE
pymt_topography/__init__.py
pymt_topography/bmi.py
pymt_topography/data/Topography/api.yaml
pymt_topography/data/Topography/bmi-topography.yaml
pymt_topography/data/Topography/info.yaml
pymt_topography/data/Topography/parameters.yaml
pymt_topography/data/Topography/run.yaml
pymt_topography-0.1.3.dist-info/RECORD
