Metadata-Version: 2.1
Name: pymt_topography
Version: 0.1.3
Summary: PyMT plugin for Topography data component
Keywords: bmi,csdms,pymt,topography,dem
Home-page: https://csdms.colorado.edu
Author: Mark Piper
Author-Email: Unknown <mark.piper@colorado.edu>
License: MIT License
Classifier: Development Status :: 4 - Beta
Classifier: Intended Audience :: Science/Research
Classifier: License :: OSI Approved :: MIT License
Classifier: Operating System :: OS Independent
Classifier: Programming Language :: Python :: 3.10
Classifier: Programming Language :: Python :: 3.11
Classifier: Programming Language :: Python :: 3.12
Classifier: Programming Language :: Python :: 3.13
Classifier: Programming Language :: Python :: 3
Classifier: Programming Language :: Python :: Implementation :: CPython
Classifier: Topic :: Scientific/Engineering :: Physics
Project-URL: Homepage, https://csdms.colorado.edu
Project-URL: Documentation, https://pymt.readthedocs.io
Project-URL: Repository, https://github.com/pymt-lab/pymt_topography
Project-URL: Changelog, https://github.com/pymt-lab/pymt_topography/blob/main/CHANGES.rst
Requires-Python: >=3.10
Requires-Dist: bmi-topography
Requires-Dist: numpy
Requires-Dist: meson; extra == "editable-install"
Requires-Dist: meson-python; extra == "editable-install"
Requires-Dist: ninja; extra == "editable-install"
Requires-Dist: black; extra == "dev"
Requires-Dist: ruff; extra == "dev"
Requires-Dist: isort; extra == "dev"
Requires-Dist: sphinx; extra == "docs"
Requires-Dist: build; extra == "build"
Requires-Dist: twine; extra == "build"
Requires-Dist: zest.releaser; extra == "build"
Requires-Dist: bmi-tester>=0.5.5; extra == "testing"
Provides-Extra: editable-install
Provides-Extra: dev
Provides-Extra: docs
Provides-Extra: build
Provides-Extra: testing
